easyhandle/__init__.py
easyhandle/client.py
easyhandle/util.py
easyhandle-0.0.7.dist-info/LICENSE
easyhandle-0.0.7.dist-info/METADATA
easyhandle-0.0.7.dist-info/WHEEL
easyhandle-0.0.7.dist-info/top_level.txt
easyhandle-0.0.7.dist-info/RECORD
