Metadata-Version: 2.1
Name: easyhandle
Version: 0.0.7
Summary: A lightweight python package for accessing handle services
Home-page: https://github.com/fwoerister/easyhandle
Author: Florian Woerister
Author-email: florian.woerister@tuwien.ac.at
License: AGPLv3+
Keywords: handle.net client python
Platform: UNKNOWN
Classifier: Development Status :: 4 - Beta
Classifier: License :: OSI Approved :: GNU Affero General Public License v3 or later (AGPLv3+)
Classifier: Programming Language :: Python :: 2
Classifier: Programming Language :: Python :: 3
